mkdocs_meta_descriptions_plugin/__init__.py
mkdocs_meta_descriptions_plugin/checker.py
mkdocs_meta_descriptions_plugin/common.py
mkdocs_meta_descriptions_plugin/export.py
mkdocs_meta_descriptions_plugin/plugin.py
mkdocs_meta_descriptions_plugin-4.0.0.dist-info/LICENSE
mkdocs_meta_descriptions_plugin-4.0.0.dist-info/METADATA
mkdocs_meta_descriptions_plugin-4.0.0.dist-info/WHEEL
mkdocs_meta_descriptions_plugin-4.0.0.dist-info/entry_points.txt
mkdocs_meta_descriptions_plugin-4.0.0.dist-info/top_level.txt
mkdocs_meta_descriptions_plugin-4.0.0.dist-info/RECORD
