Metadata-Version: 2.2
Name: mkdocs-meta-descriptions-plugin
Version: 4.0.0
Summary: Generate meta descriptions from the first paragraphs in your MkDocs pages
Home-page: https://github.com/prcr/mkdocs-meta-descriptions-plugin
Author: Paulo Ribeiro
Author-email: paulo@diffraction.pt
License: MIT
Keywords: mkdocs meta description seo paragraph
Classifier: Development Status :: 5 - Production/Stable
Classifier: Intended Audience :: Developers
Classifier: Intended Audience :: Information Technology
Classifier: License :: OSI Approved :: MIT License
Classifier: Programming Language :: Python
Classifier: Programming Language :: Python :: 3 :: Only
Classifier: Programming Language :: Python :: 3.9
Classifier: Programming Language :: Python :: 3.10
Classifier: Programming Language :: Python :: 3.11
Classifier: Programming Language :: Python :: 3.12
Classifier: Programming Language :: Python :: 3.13
Requires-Python: >=3
License-File: LICENSE
Requires-Dist: mkdocs>=1.1
Requires-Dist: pymdown-extensions>=7.0
Requires-Dist: beautifulsoup4>=4.9
Requires-Dist: packaging
Dynamic: author
Dynamic: author-email
Dynamic: classifier
Dynamic: description
Dynamic: description-content-type
Dynamic: home-page
Dynamic: keywords
Dynamic: license
Dynamic: requires-dist
Dynamic: requires-python
Dynamic: summary
